{
  "phase": "0_baseline",
  "target": "obs_subscore",
  "fm_obs_loocv": {
    "mae": 4.062,
    "rmse": 5.356,
    "r": 0.452,
    "r_p": 3e-06,
    "rho": 0.435,
    "ccc": 0.256,
    "r2": 0.182,
    "cal_slope": 0.141,
    "cal_intercept": 9.117,
    "n": 98,
    "quartiles": [
      {
        "mae": 8.435,
        "rmse": 8.544,
        "r": 0.353,
        "r_p": 0.491855,
        "rho": 0.395,
        "ccc": 0.014,
        "r2": -53.75,
        "cal_slope": 0.377,
        "cal_intercept": 9.059,
        "n": 6,
        "label": "Q1 (<4)",
        "bias": 8.44
      },
      {
        "mae": 4.015,
        "rmse": 4.449,
        "r": -0.307,
        "r_p": 0.134932,
        "rho": -0.232,
        "ccc": -0.045,
        "r2": -15.585,
        "cal_slope": -0.358,
        "cal_intercept": 12.058,
        "n": 25,
        "label": "Q2 (4-8)",
        "bias": 4.02
      },
      {
        "mae": 1.866,
        "rmse": 2.388,
        "r": 0.263,
        "r_p": 0.105219,
        "rho": 0.222,
        "ccc": 0.262,
        "r2": -0.562,
        "cal_slope": 0.278,
        "cal_intercept": 7.593,
        "n": 39,
        "label": "Q3 (8-14)",
        "bias": -0.13
      },
      {
        "mae": 6.226,
        "rmse": 7.69,
        "r": 0.378,
        "r_p": 0.047283,
        "rho": 0.28,
        "ccc": 0.092,
        "r2": -1.494,
        "cal_slope": 0.126,
        "cal_intercept": 9.444,
        "n": 28,
        "label": "Q4 (>=14)",
        "bias": -6.23
      }
    ],
    "time_s": 649.3
  },
  "demo_obs_loocv": {
    "mae": 4.289,
    "rmse": 5.452,
    "r": "0.401",
    "r_p": 4.3e-05,
    "rho": 0.288,
    "ccc": 0.318,
    "r2": 0.152,
    "cal_slope": 0.197,
    "cal_intercept": 8.79,
    "n": 98,
    "quartiles": [
      {
        "mae": 8.516,
        "rmse": 9.023,
        "r": "0.565",
        "r_p": 0.242518,
        "rho": 0.698,
        "ccc": 0.053,
        "r2": -60.067,
        "cal_slope": 1.703,
        "cal_intercept": 7.812,
        "n": 6,
        "label": "Q1 (<4)",
        "bias": 8.52
      },
      {
        "mae": 4.325,
        "rmse": 5.013,
        "r": "0.037",
        "r_p": 0.861896,
        "rho": 0.085,
        "ccc": 0.008,
        "r2": -20.057,
        "cal_slope": 0.087,
        "cal_intercept": 9.573,
        "n": 25,
        "label": "Q2 (4-8)",
        "bias": 4.17
      },
      {
        "mae": 2.301,
        "rmse": 2.837,
        "r": "0.187",
        "r_p": 0.253153,
        "rho": 0.153,
        "ccc": 0.181,
        "r2": -1.206,
        "cal_slope": 0.243,
        "cal_intercept": 8.301,
        "n": 39,
        "label": "Q3 (8-14)",
        "bias": 0.21
      },
      {
        "mae": 6.12,
        "rmse": 7.276,
        "r": "0.483",
        "r_p": 0.009261,
        "rho": 0.488,
        "ccc": 0.22,
        "r2": -1.233,
        "cal_slope": 0.315,
        "cal_intercept": 6.438,
        "n": 28,
        "label": "Q4 (>=14)",
        "bias": -5.84
      }
    ],
    "time_s": 0.2
  },
  "cached_direct_obs": {
    "mae": 1.769,
    "rmse": 2.235,
    "r2": 0.37,
    "ccc": 0.56,
    "r": 0.667,
    "spearman_rho": 0.556,
    "spearman_p": 0.0,
    "mae_sd": 0.628,
    "nrmse": 0.16,
    "cal_slope": 0.401,
    "cal_intercept": 1.716,
    "n": 94
  }
}